spices/__init__.py
spices/cli.py
spices-0.0.3.dist-info/AUTHORS.rst
spices-0.0.3.dist-info/LICENSE
spices-0.0.3.dist-info/METADATA
spices-0.0.3.dist-info/WHEEL
spices-0.0.3.dist-info/top_level.txt
spices-0.0.3.dist-info/RECORD
