Metadata-Version: 2.1
Name: spices
Version: 0.0.3
Summary: A universal dependency resolver:one installer to rule them all.
Home-page: https://github.com/LuisAlejandro/spices
Author: Luis Alejandro Martínez Faneyth
Author-email: luis@collagelabs.org
License: UNKNOWN
Keywords: odoo,requirements
Platform: UNKNOWN
Classifier: Development Status :: 5 - Production/Stable
Classifier: Intended Audience :: Developers
Classifier: License :: OSI Approved :: GNU General Public License v3 (GPLv3)
Classifier: Natural Language :: English
Classifier: Programming Language :: Python :: 3
Classifier: Programming Language :: Python :: 3.8
Classifier: Programming Language :: Python :: 3.9
Classifier: Programming Language :: Python :: 3.10
Classifier: Programming Language :: Python :: 3.11
License-File: LICENSE
License-File: AUTHORS.rst
Requires-Dist: pyyaml
